barlibs/tiingo/__init__.py
barlibs/tiingo/engine.py
barlibs/tiingo/utils.py
bardata_tiingo-0.0.0.dist-info/METADATA
bardata_tiingo-0.0.0.dist-info/WHEEL
bardata_tiingo-0.0.0.dist-info/entry_points.txt
bardata_tiingo-0.0.0.dist-info/RECORD
