Metadata-Version: 2.4
Name: bardata-tiingo
Version: 0.0.0
Summary: Bardata engine for Tiingo
License-Expression: MIT
Requires-Python: >=3.10
Requires-Dist: pandas
Requires-Dist: tiingo
